e2x_exam_sheets/__about__.py
e2x_exam_sheets/__init__.py
e2x_exam_sheets/examsheetgenerator.py
e2x_exam_sheets/static/css/container.css
e2x_exam_sheets/static/css/elements.css
e2x_exam_sheets/static/css/hashcode.css
e2x_exam_sheets/static/css/seating_card.css
e2x_exam_sheets/static/css/supervision_list.css
e2x_exam_sheets/static/locales/labels_de.json
e2x_exam_sheets/static/locales/labels_en.json
e2x_exam_sheets/static/templates/exam_sheet copy.html
e2x_exam_sheets/static/templates/exam_sheet.html
e2x_exam_sheets/static/templates/supervision_list.html
e2x_exam_sheets/static/templates/macros/hashcode_table.html
e2x_exam_sheets/static/templates/sheets/login_sheet.html
e2x_exam_sheets/static/templates/sheets/notes_sheet.html
e2x_exam_sheets/static/templates/sheets/seating_sheet.html
e2x_exam_sheets/static/templates/sheets/take_home_sheet.html
e2x_exam_sheets-0.1.1.dist-info/METADATA
e2x_exam_sheets-0.1.1.dist-info/WHEEL
e2x_exam_sheets-0.1.1.dist-info/licenses/LICENSE.txt
e2x_exam_sheets-0.1.1.dist-info/RECORD
