Metadata-Version: 2.4
Name: e2x-exam-sheets
Version: 0.1.1
Project-URL: Documentation, https://github.com/Digiklausur/e2x-exam-sheets#readme
Project-URL: Issues, https://github.com/Digiklausur/e2x-exam-sheets/issues
Project-URL: Source, https://github.com/Digiklausur/e2x-exam-sheets
Author-email: Tim Metzler <tim.metzler@h-brs.de>
License-Expression: MIT
License-File: LICENSE.txt
Classifier: Development Status :: 4 - Beta
Classifier: Programming Language :: Python
Classifier: Programming Language :: Python :: 3.8
Classifier: Programming Language :: Python :: 3.9
Classifier: Programming Language :: Python :: 3.10
Classifier: Programming Language :: Python :: 3.11
Classifier: Programming Language :: Python :: 3.12
Classifier: Programming Language :: Python :: Implementation :: CPython
Classifier: Programming Language :: Python :: Implementation :: PyPy
Requires-Python: >=3.8
Requires-Dist: jinja2
Requires-Dist: pandas
Requires-Dist: pypdf2
Requires-Dist: weasyprint>=62
Provides-Extra: dev
Requires-Dist: pre-commit; extra == 'dev'
Requires-Dist: pydata-sphinx-theme; extra == 'dev'
Requires-Dist: ruff; extra == 'dev'
Requires-Dist: sphinx; extra == 'dev'
Requires-Dist: tbump; extra == 'dev'
